[
    {
        "Sr_No": 1,
        "Name": "Pizza Freakers",
        "img_url": "https://source.unsplash.com/random/200x200?sig=3",
        "Ratings": 4,
        "Review": ["Sandwiches packed to perfection. Sauce dripping, napkins flying"],
        "Location": "Chandigarh",
        "Created_by" : "Simran"
    },
    {
        "Sr_No": 2,
        "Name": "The Urban Pind",
        "img_url": "https://source.unsplash.com/random/200x200?sig=3",
        "Ratings": 4,
        "Review":[ "Milkshakes that defy gravity. Sip, slurp, and surrender to sweetness"],
        "Location": "Chandigarh",
        "Created_by" : "Simran"
    },
    {
        "Sr_No": 3,
        "Name": "Burgerama",
        "img_url": "https://source.unsplash.com/random/200x200?sig=3",
        "Ratings": 4,
        "Review": ["Burgers drowning in cheese and chili. Prepare for a delicious mess!"],
        "Location": "Chandigarh",
        "Created_by" :"swati"
    },
    {
        "Sr_No": 4,
        "Name": "Wok N Tok",
        "img_url": "https://source.unsplash.com/random/200x200?sig=3",
        "Ratings": 4,
        "Review": ["Tacos with a tropical twist. Aloha to flavor town"],
        "Location": "Chandigarh",
        "Created_by" : "Akshat"
    },
    {
        "Sr_No": 5,
        "Name": "Rustik Punjab",
        "img_url": "https://source.unsplash.com/random/200x200?sig=3",
        "Ratings": 4,
        "Review": ["Dumplings to die for. So good, you'll want to marry them"],
        "Location": "Punjab",
        "Created_by" :"Anushka"
    },
    {
        "Sr_No": 6,
        "Name": "Crystal Restraunt",
        "img_url": "https://source.unsplash.com/random/200x200?sig=3",
        "Ratings": 4,
        "Review":[ "Fluffy clouds of pancakes. Toppings galore, coma guaranteed"],
        "Location": "Punjab",
        "Created_by" : "swati"
    },
    {
        "Sr_No": 7,
        "Name": "Punjab Province",
        "img_url": "https://source.unsplash.com/random/200x200?sig=3",
        "Ratings": 4,
        "Review": ["Tiny burgers, big flavor. Like a carnival for your taste buds"],
        "Location": "Punjab",
        "Created_by" : "Akshat"
    },
    {
        "Sr_No": 8,
        "Name": "Urban Rasoi",
        "img_url": "https://source.unsplash.com/random/200x200?sig=3",
        "Ratings": 4,
        "Review": ["Grandma's secret recipe meets a sprinkle of mystery. Delightfully confusing"],
        "Location": "Punjab",
        "Created_by" : "Simran"
    },
    {
        "Sr_No": 9,
        "Name": "Dragon House",
        "img_url": "https://source.unsplash.com/random/200x200?sig=3",
        "Ratings": 4,
        "Review":[ "Spaghetti on a pizza? It's a pasta lover's fever dream"],
        "Location": "Jaipur",
        "Created_by" : "Alisha"
    },
    {
        "Sr_No": 10,
        "Name": "Suvarna Mahal",
        "img_url": "https://source.unsplash.com/random/200x200?sig=3",
        "Ratings": 4,
        "Review": ["Transported to Mexico with each bite. Margaritas not included"],
        "Location": "Jaipur",
        "Created_by" :"Alisha"
    },
    {
        "Sr_No": 11,
        "Name": "Peacock Restraunt",
        "img_url": "https://source.unsplash.com/random/200x200?sig=3",
        "Ratings": 4,
        "Review": ["Burritos as big as flotation devices. Chew carefully to avoid concussion"],
        "Location": "Jaipur",
        "Created_by" : "Anushka"

    },
    {
        "Sr_No": 12,
        "Name": "Kebab Nation",
        "img_url": "https://source.unsplash.com/random/200x200?sig=3",
        "Ratings": 4,
        "Review": ["The 'Cowabunga Burger' a beefy beast. Roll out the door afterward"],
        "Location": "Jaipur",
        "Created_by" :"swati"
    },
    {
        "Sr_No": 13,
        "Name": "Tamra Restraunt",
        "img_url": "https://source.unsplash.com/random/200x200?sig=3",
        "Ratings": 4,
        "Review": ["Secret society of sushi lovers. Don't ask about the 'mystery roll"],
        "Location": "Delhi",
        "Created_by" : "swati"
    },
    {
        "Sr_No": 14,
        "Name": "Mughlai Junction",
        "img_url": "https://source.unsplash.com/random/200x200?sig=3",
        "Ratings": 4,
        "Review": ["Nachos reaching the heavens. Watch out for seagulls"],
        "Location": "Delhi",
        "Created_by" : "Anushka"
    },
    {
        "Sr_No": 15,
        "Name": "Zaffran",
        "img_url": "https://source.unsplash.com/random/200x200?sig=3",
        "Ratings": 4,
        "Review": ["Fried chicken like a thousand suns. Napkins required for the mess"],
        "Location": "Delhi",
        "Created_by" : "Akshat"
    },
    {
        "Sr_No": 16,
        "Name": "Minar Restraunt",
        "img_url": "https://source.unsplash.com/random/200x200?sig=3",
        "Ratings": 4,
        "Review": ["Fluffy clouds of pancakes. Toppings galore, coma guaranteed"],
        "Location": "Delhi",
        "Created_by" : "Akshat"
    }
]
